[
  {
    "state": "CA",
    "total_stations": 20644,
    "open_stations": 20243,
    "planned_stations": 76,
    "temp_unavailable_stations": 325,
    "total_level2_ports": 56749,
    "stations_with_dc_fast": 3183,
    "total_dc_fast_ports_partial": 18496,
    "first_station_date": "1995-08-30"
  },
  {
    "state": "NY",
    "total_stations": 5589,
    "open_stations": 5395,
    "planned_stations": 34,
    "temp_unavailable_stations": 160,
    "total_level2_ports": 17922,
    "stations_with_dc_fast": 896,
    "total_dc_fast_ports_partial": 3146,
    "first_station_date": "2008-07-01"
  },
  {
    "state": "FL",
    "total_stations": 4625,
    "open_stations": 4522,
    "planned_stations": 11,
    "temp_unavailable_stations": 92,
    "total_level2_ports": 10957,
    "stations_with_dc_fast": 1088,
    "total_dc_fast_ports_partial": 4705,
    "first_station_date": "2001-08-21"
  },
  {
    "state": "MA",
    "total_stations": 4494,
    "open_stations": 4419,
    "planned_stations": 7,
    "temp_unavailable_stations": 68,
    "total_level2_ports": 9963,
    "stations_with_dc_fast": 372,
    "total_dc_fast_ports_partial": 1775,
    "first_station_date": "2009-03-15"
  },
  {
    "state": "TX",
    "total_stations": 4104,
    "open_stations": 3978,
    "planned_stations": 36,
    "temp_unavailable_stations": 90,
    "total_level2_ports": 8402,
    "stations_with_dc_fast": 946,
    "total_dc_fast_ports_partial": 4783,
    "first_station_date": "2010-12-30"
  },
  {
    "state": "WA",
    "total_stations": 3130,
    "open_stations": 3068,
    "planned_stations": 11,
    "temp_unavailable_stations": 51,
    "total_level2_ports": 6907,
    "stations_with_dc_fast": 476,
    "total_dc_fast_ports_partial": 2021,
    "first_station_date": "2008-02-15"
  },
  {
    "state": "CO",
    "total_stations": 2893,
    "open_stations": 2835,
    "planned_stations": 12,
    "temp_unavailable_stations": 46,
    "total_level2_ports": 6471,
    "stations_with_dc_fast": 482,
    "total_dc_fast_ports_partial": 1604,
    "first_station_date": "2010-04-14"
  },
  {
    "state": "GA",
    "total_stations": 2471,
    "open_stations": 2431,
    "planned_stations": 7,
    "temp_unavailable_stations": 33,
    "total_level2_ports": 6156,
    "stations_with_dc_fast": 571,
    "total_dc_fast_ports_partial": 2086,
    "first_station_date": "2010-12-15"
  },
  {
    "state": "MI",
    "total_stations": 2140,
    "open_stations": 2087,
    "planned_stations": 13,
    "temp_unavailable_stations": 40,
    "total_level2_ports": 4347,
    "stations_with_dc_fast": 363,
    "total_dc_fast_ports_partial": 1613,
    "first_station_date": "2011-04-15"
  },
  {
    "state": "PA",
    "total_stations": 2134,
    "open_stations": 2070,
    "planned_stations": 19,
    "temp_unavailable_stations": 45,
    "total_level2_ports": 4284,
    "stations_with_dc_fast": 387,
    "total_dc_fast_ports_partial": 1836,
    "first_station_date": "2011-08-19"
  },
  {
    "state": "OH",
    "total_stations": 2107,
    "open_stations": 2036,
    "planned_stations": 24,
    "temp_unavailable_stations": 47,
    "total_level2_ports": 4314,
    "stations_with_dc_fast": 391,
    "total_dc_fast_ports_partial": 1468,
    "first_station_date": "2010-12-15"
  },
  {
    "state": "VA",
    "total_stations": 2059,
    "open_stations": 1983,
    "planned_stations": 38,
    "temp_unavailable_stations": 38,
    "total_level2_ports": 4644,
    "stations_with_dc_fast": 422,
    "total_dc_fast_ports_partial": 1732,
    "first_station_date": "2011-03-15"
  },
  {
    "state": "NC",
    "total_stations": 2048,
    "open_stations": 2001,
    "planned_stations": 8,
    "temp_unavailable_stations": 39,
    "total_level2_ports": 4457,
    "stations_with_dc_fast": 382,
    "total_dc_fast_ports_partial": 1795,
    "first_station_date": "2010-01-01"
  },
  {
    "state": "NJ",
    "total_stations": 1922,
    "open_stations": 1859,
    "planned_stations": 16,
    "temp_unavailable_stations": 47,
    "total_level2_ports": 4587,
    "stations_with_dc_fast": 356,
    "total_dc_fast_ports_partial": 2043,
    "first_station_date": "2010-05-15"
  },
  {
    "state": "IL",
    "total_stations": 1857,
    "open_stations": 1827,
    "planned_stations": 2,
    "temp_unavailable_stations": 28,
    "total_level2_ports": 3576,
    "stations_with_dc_fast": 343,
    "total_dc_fast_ports_partial": 2501,
    "first_station_date": "2009-01-15"
  },
  {
    "state": "MD",
    "total_stations": 1844,
    "open_stations": 1803,
    "planned_stations": 4,
    "temp_unavailable_stations": 37,
    "total_level2_ports": 4638,
    "stations_with_dc_fast": 351,
    "total_dc_fast_ports_partial": 1423,
    "first_station_date": "2011-03-15"
  },
  {
    "state": "OR",
    "total_stations": 1757,
    "open_stations": 1717,
    "planned_stations": 10,
    "temp_unavailable_stations": 30,
    "total_level2_ports": 3273,
    "stations_with_dc_fast": 386,
    "total_dc_fast_ports_partial": 1292,
    "first_station_date": "2008-10-15"
  },
  {
    "state": "CT",
    "total_stations": 1684,
    "open_stations": 1664,
    "planned_stations": 4,
    "temp_unavailable_stations": 16,
    "total_level2_ports": 4421,
    "stations_with_dc_fast": 195,
    "total_dc_fast_ports_partial": 773,
    "first_station_date": "2010-01-01"
  },
  {
    "state": "AZ",
    "total_stations": 1598,
    "open_stations": 1559,
    "planned_stations": 2,
    "temp_unavailable_stations": 37,
    "total_level2_ports": 3559,
    "stations_with_dc_fast": 259,
    "total_dc_fast_ports_partial": 1428,
    "first_station_date": "2011-03-15"
  },
  {
    "state": "MO",
    "total_stations": 1397,
    "open_stations": 1370,
    "planned_stations": 1,
    "temp_unavailable_stations": 26,
    "total_level2_ports": 2559,
    "stations_with_dc_fast": 210,
    "total_dc_fast_ports_partial": 792,
    "first_station_date": "2010-01-15"
  },
  {
    "state": "TN",
    "total_stations": 1255,
    "open_stations": 1215,
    "planned_stations": 4,
    "temp_unavailable_stations": 36,
    "total_level2_ports": 2410,
    "stations_with_dc_fast": 245,
    "total_dc_fast_ports_partial": 969,
    "first_station_date": "2010-01-20"
  },
  {
    "state": "MN",
    "total_stations": 1148,
    "open_stations": 1133,
    "planned_stations": 1,
    "temp_unavailable_stations": 14,
    "total_level2_ports": 2194,
    "stations_with_dc_fast": 234,
    "total_dc_fast_ports_partial": 974,
    "first_station_date": "2011-10-17"
  },
  {
    "state": "UT",
    "total_stations": 1048,
    "open_stations": 1030,
    "planned_stations": 1,
    "temp_unavailable_stations": 17,
    "total_level2_ports": 2395,
    "stations_with_dc_fast": 213,
    "total_dc_fast_ports_partial": 799,
    "first_station_date": "2010-12-15"
  },
  {
    "state": "WI",
    "total_stations": 895,
    "open_stations": 879,
    "planned_stations": 0,
    "temp_unavailable_stations": 16,
    "total_level2_ports": 1495,
    "stations_with_dc_fast": 197,
    "total_dc_fast_ports_partial": 815,
    "first_station_date": "2009-08-15"
  },
  {
    "state": "IN",
    "total_stations": 763,
    "open_stations": 744,
    "planned_stations": 7,
    "temp_unavailable_stations": 12,
    "total_level2_ports": 1514,
    "stations_with_dc_fast": 174,
    "total_dc_fast_ports_partial": 915,
    "first_station_date": "2012-01-31"
  },
  {
    "state": "SC",
    "total_stations": 740,
    "open_stations": 720,
    "planned_stations": 1,
    "temp_unavailable_stations": 19,
    "total_level2_ports": 1395,
    "stations_with_dc_fast": 213,
    "total_dc_fast_ports_partial": 890,
    "first_station_date": "2010-12-15"
  },
  {
    "state": "ME",
    "total_stations": 691,
    "open_stations": 682,
    "planned_stations": 0,
    "temp_unavailable_stations": 9,
    "total_level2_ports": 1313,
    "stations_with_dc_fast": 168,
    "total_dc_fast_ports_partial": 371,
    "first_station_date": "2011-11-30"
  },
  {
    "state": "NV",
    "total_stations": 686,
    "open_stations": 680,
    "planned_stations": 1,
    "temp_unavailable_stations": 5,
    "total_level2_ports": 1845,
    "stations_with_dc_fast": 200,
    "total_dc_fast_ports_partial": 1159,
    "first_station_date": "2011-12-31"
  },
  {
    "state": "AL",
    "total_stations": 673,
    "open_stations": 651,
    "planned_stations": 5,
    "temp_unavailable_stations": 17,
    "total_level2_ports": 1294,
    "stations_with_dc_fast": 238,
    "total_dc_fast_ports_partial": 882,
    "first_station_date": "2011-03-15"
  },
  {
    "state": "KS",
    "total_stations": 622,
    "open_stations": 612,
    "planned_stations": 0,
    "temp_unavailable_stations": 10,
    "total_level2_ports": 1188,
    "stations_with_dc_fast": 85,
    "total_dc_fast_ports_partial": 364,
    "first_station_date": "2011-06-01"
  },
  {
    "state": "VT",
    "total_stations": 565,
    "open_stations": 555,
    "planned_stations": 0,
    "temp_unavailable_stations": 10,
    "total_level2_ports": 1177,
    "stations_with_dc_fast": 123,
    "total_dc_fast_ports_partial": 296,
    "first_station_date": "2004-01-15"
  },
  {
    "state": "IA",
    "total_stations": 516,
    "open_stations": 506,
    "planned_stations": 0,
    "temp_unavailable_stations": 10,
    "total_level2_ports": 779,
    "stations_with_dc_fast": 110,
    "total_dc_fast_ports_partial": 550,
    "first_station_date": "2010-05-15"
  },
  {
    "state": "NM",
    "total_stations": 504,
    "open_stations": 496,
    "planned_stations": 4,
    "temp_unavailable_stations": 4,
    "total_level2_ports": 750,
    "stations_with_dc_fast": 153,
    "total_dc_fast_ports_partial": 562,
    "first_station_date": "2012-05-12"
  },
  {
    "state": "HI",
    "total_stations": 448,
    "open_stations": 418,
    "planned_stations": 13,
    "temp_unavailable_stations": 17,
    "total_level2_ports": 998,
    "stations_with_dc_fast": 72,
    "total_dc_fast_ports_partial": 189,
    "first_station_date": "2011-03-15"
  },
  {
    "state": "OK",
    "total_stations": 445,
    "open_stations": 426,
    "planned_stations": 2,
    "temp_unavailable_stations": 17,
    "total_level2_ports": 910,
    "stations_with_dc_fast": 210,
    "total_dc_fast_ports_partial": 1029,
    "first_station_date": "2010-01-01"
  },
  {
    "state": "KY",
    "total_stations": 430,
    "open_stations": 411,
    "planned_stations": 13,
    "temp_unavailable_stations": 6,
    "total_level2_ports": 850,
    "stations_with_dc_fast": 96,
    "total_dc_fast_ports_partial": 412,
    "first_station_date": "2012-01-31"
  },
  {
    "state": "DC",
    "total_stations": 414,
    "open_stations": 401,
    "planned_stations": 0,
    "temp_unavailable_stations": 13,
    "total_level2_ports": 1348,
    "stations_with_dc_fast": 52,
    "total_dc_fast_ports_partial": 61,
    "first_station_date": "2011-12-01"
  },
  {
    "state": "AR",
    "total_stations": 403,
    "open_stations": 393,
    "planned_stations": 0,
    "temp_unavailable_stations": 10,
    "total_level2_ports": 895,
    "stations_with_dc_fast": 82,
    "total_dc_fast_ports_partial": 267,
    "first_station_date": "2011-06-01"
  },
  {
    "state": "RI",
    "total_stations": 372,
    "open_stations": 365,
    "planned_stations": 0,
    "temp_unavailable_stations": 7,
    "total_level2_ports": 798,
    "stations_with_dc_fast": 38,
    "total_dc_fast_ports_partial": 130,
    "first_station_date": "2011-10-31"
  },
  {
    "state": "LA",
    "total_stations": 337,
    "open_stations": 328,
    "planned_stations": 0,
    "temp_unavailable_stations": 9,
    "total_level2_ports": 605,
    "stations_with_dc_fast": 93,
    "total_dc_fast_ports_partial": 386,
    "first_station_date": "2011-07-15"
  },
  {
    "state": "NE",
    "total_stations": 332,
    "open_stations": 328,
    "planned_stations": 0,
    "temp_unavailable_stations": 4,
    "total_level2_ports": 502,
    "stations_with_dc_fast": 73,
    "total_dc_fast_ports_partial": 237,
    "first_station_date": "2012-01-31"
  },
  {
    "state": "NH",
    "total_stations": 330,
    "open_stations": 322,
    "planned_stations": 0,
    "temp_unavailable_stations": 8,
    "total_level2_ports": 527,
    "stations_with_dc_fast": 83,
    "total_dc_fast_ports_partial": 326,
    "first_station_date": "2011-04-15"
  },
  {
    "state": "ID",
    "total_stations": 272,
    "open_stations": 271,
    "planned_stations": 0,
    "temp_unavailable_stations": 1,
    "total_level2_ports": 478,
    "stations_with_dc_fast": 79,
    "total_dc_fast_ports_partial": 280,
    "first_station_date": "2012-01-31"
  },
  {
    "state": "DE",
    "total_stations": 265,
    "open_stations": 245,
    "planned_stations": 9,
    "temp_unavailable_stations": 11,
    "total_level2_ports": 529,
    "stations_with_dc_fast": 41,
    "total_dc_fast_ports_partial": 303,
    "first_station_date": "2012-01-31"
  },
  {
    "state": "MS",
    "total_stations": 251,
    "open_stations": 245,
    "planned_stations": 1,
    "temp_unavailable_stations": 5,
    "total_level2_ports": 455,
    "stations_with_dc_fast": 93,
    "total_dc_fast_ports_partial": 332,
    "first_station_date": "2012-01-31"
  },
  {
    "state": "WV",
    "total_stations": 215,
    "open_stations": 209,
    "planned_stations": 1,
    "temp_unavailable_stations": 5,
    "total_level2_ports": 391,
    "stations_with_dc_fast": 66,
    "total_dc_fast_ports_partial": 219,
    "first_station_date": "2010-12-15"
  },
  {
    "state": "MT",
    "total_stations": 167,
    "open_stations": 162,
    "planned_stations": 1,
    "temp_unavailable_stations": 4,
    "total_level2_ports": 239,
    "stations_with_dc_fast": 63,
    "total_dc_fast_ports_partial": 255,
    "first_station_date": "2013-06-30"
  },
  {
    "state": "WY",
    "total_stations": 132,
    "open_stations": 131,
    "planned_stations": 0,
    "temp_unavailable_stations": 1,
    "total_level2_ports": 178,
    "stations_with_dc_fast": 36,
    "total_dc_fast_ports_partial": 169,
    "first_station_date": "2013-03-31"
  },
  {
    "state": "SD",
    "total_stations": 126,
    "open_stations": 123,
    "planned_stations": 0,
    "temp_unavailable_stations": 3,
    "total_level2_ports": 192,
    "stations_with_dc_fast": 51,
    "total_dc_fast_ports_partial": 162,
    "first_station_date": "2012-01-31"
  },
  {
    "state": "ND",
    "total_stations": 115,
    "open_stations": 112,
    "planned_stations": 0,
    "temp_unavailable_stations": 3,
    "total_level2_ports": 136,
    "stations_with_dc_fast": 27,
    "total_dc_fast_ports_partial": 150,
    "first_station_date": "2012-10-25"
  },
  {
    "state": "AK",
    "total_stations": 86,
    "open_stations": 85,
    "planned_stations": 0,
    "temp_unavailable_stations": 1,
    "total_level2_ports": 124,
    "stations_with_dc_fast": 36,
    "total_dc_fast_ports_partial": 99,
    "first_station_date": "2014-01-01"
  },
  {
    "state": "PR",
    "total_stations": 28,
    "open_stations": 25,
    "planned_stations": 0,
    "temp_unavailable_stations": 3,
    "total_level2_ports": 53,
    "stations_with_dc_fast": 0,
    "total_dc_fast_ports_partial": 0,
    "first_station_date": "2021-01-27"
  }
]